MANIFEST.in
README
setup.py
orbfit/aeiderivs.c
orbfit/covsrt.c
orbfit/dms.c
orbfit/ephem_earth.c
orbfit/ephem_read.h
orbfit/ephem_types.h
orbfit/gasdev.c
orbfit/gaussj.c
orbfit/lubksb.c
orbfit/ludcmp.c
orbfit/mrqcof_orbit.c
orbfit/mrqmin_orbit.c
orbfit/nrutil.c
orbfit/nrutil.h
orbfit/orbfit.h
orbfit/orbfit1.c
orbfit/orbfit2.c
orbfit/orbfitmodule.c
orbfit/ran1.c
orbfit/transforms.c
scripts/minor_planet_ephemeris.py
src/mp_ephem/__init__.py
src/mp_ephem/__version__.py
src/mp_ephem/bk_orbit.py
src/mp_ephem/ephem.py
src/mp_ephem/ephem_target.py
src/mp_ephem/horizons.py
src/mp_ephem/mpc.py
src/mp_ephem/ssos.py
src/mp_ephem/time_mpc.py
src/mp_ephem.egg-info/PKG-INFO
src/mp_ephem.egg-info/SOURCES.txt
src/mp_ephem.egg-info/dependency_links.txt
src/mp_ephem.egg-info/requires.txt
src/mp_ephem.egg-info/top_level.txt
src/mp_ephem/data/binEphem.405_32
src/mp_ephem/data/binEphem.405_64
src/mp_ephem/data/observatories.dat
test/test_orbit.py
test/test_query.py
test/test_time.py